{"@context": "http://schema.org", "@type": "Organization", "name": "hexafarms", "url": "https://de.linkedin.com/company/hexafarms", "address": {"type": "PostalAddress", "addressLocality": "Berlin", "postalCode": "12435", "addressCountry": "DE"}, "description": "Hexafarms is an Ag-Tech Startup that develops software for indoor commercial food production. Our SaaS harvests data and leverages AI to monitor, control, and optimize greenhouses and vertical indoor farms in real-time. Our vision is to empower a farms across the globe to run as efficiently as possible. ", "numberOfEmployees": {"value": 11, "@type": "QuantitativeValue"}, "logo": {"contentUrl": "https://media.licdn.com/dms/image/C4D0BAQGf2ZgSH93RVQ/company-logo_200_200/0/1640098948343/hexa_farms_logo?e=2147483647&v=beta&t=MmSbTpbz7k8e2suNOWNSPgfDky3PxyWWzCM1lYz6gSc", "description": "hexafarms", "@type": "ImageObject"}, "slogan": "AI-powered hyper-efficient commercial food production", "sameAs": "https://www.hexafarms.com"}